Mdataset/__init__.py
Mdataset/Audio/__init__.py
Mdataset/Audio/meta_audio.py
Mdataset/Audio/transcription.py
Mdataset/Censored/__init__.py
Mdataset/Censored/launch.py
Mdataset/Circuit/__init__.py
Mdataset/Circuit/deep_circuit.py
Mdataset/Circuit/multihead_circuit.py
Mdataset/DWeb/__init__.py
Mdataset/DWeb/dsearch.py
Mdataset/FTransfer/Flaunch.py
Mdataset/FTransfer/__init__.py
Mdataset/Huggingface/__init__.py
Mdataset/Huggingface/face_dataset.py
Mdataset/Kaggle/__init__.py
Mdataset/Kaggle/kaggle_load.py
Mdataset/Multithread/__init__.py
Mdataset/Multithread/cpu_info.py
Mdataset/Optical/__init__.py
Mdataset/Optical/displaytext.py
Mdataset/Optical/pdf2text.py
Mdataset/Scrapping/__init__.py
Mdataset/Scrapping/allscrap.py
Mdataset/Scrapping/chan.py
Mdataset/Scrapping/gscholar.py
Mdataset/Synthetic/__init__.py
Mdataset/Synthetic/petals_generate.py
Mdataset/Tabular/__init__.py
Mdataset/Tabular/synload.py
Mdataset/Tabular/tab_train.py
Mdataset/Tabular/tabledata.py
Mdataset/Youdownload/__init__.py
Mdataset/Youdownload/audio_downloader.py
Mdataset/Youdownload/media_download.py
mdataset-0.2.0.dist-info/METADATA
mdataset-0.2.0.dist-info/WHEEL
mdataset-0.2.0.dist-info/top_level.txt
mdataset-0.2.0.dist-info/RECORD
