Metadata-Version: 2.1
Name: mdataset
Version: 0.2.0
Author: TAWSIF AHMED
Author-email: sleeping4cat@outlook.com
Requires-Dist: nougat-ocr
Requires-Dist: transformers
Requires-Dist: idisplay
Requires-Dist: torch
Requires-Dist: sentencepiece
Requires-Dist: duckduckgo-search
Requires-Dist: BASC-py4chan
Requires-Dist: pytube
Requires-Dist: tqdm
Requires-Dist: flask
Requires-Dist: requests
Requires-Dist: beautifulsoup4
Requires-Dist: datasets
Requires-Dist: petals
Requires-Dist: kaggle
Requires-Dist: ydata-synthetic (==1.3.0)
Requires-Dist: scap4chan
